Metadata-Version: 1.0
Name: matthew
Version: 1.0.0
Summary: Matthew
Home-page: UNKNOWN
Author: Matthew
Author-email: automatthew@gmail.com
License: MIT
Platform: UNKNOWN
